mcp100_demo_text/__init__.py
mcp100_demo_text-0.1.0.dist-info/METADATA
mcp100_demo_text-0.1.0.dist-info/WHEEL
mcp100_demo_text-0.1.0.dist-info/entry_points.txt
mcp100_demo_text-0.1.0.dist-info/RECORD
