Metadata-Version: 2.4
Name: mcp100-demo-text
Version: 0.1.0
Summary: Add your description here
Author-email: XDY <examle@123.com>
Requires-Python: >=3.13
Requires-Dist: httpx>=0.28.1
Requires-Dist: mcp[cli]>=1.11.0
